openhab_pythonrule_engine/__init__.py
openhab_pythonrule_engine/app.py
openhab_pythonrule_engine/cache.py
openhab_pythonrule_engine/condition.py
openhab_pythonrule_engine/cron_processor.py
openhab_pythonrule_engine/eventbus_consumer.py
openhab_pythonrule_engine/invoke.py
openhab_pythonrule_engine/item_change_processor.py
openhab_pythonrule_engine/item_registry.py
openhab_pythonrule_engine/loaded_rule_processor.py
openhab_pythonrule_engine/processor.py
openhab_pythonrule_engine/rule.py
openhab_pythonrule_engine/rule_engine.py
openhab_pythonrule_engine/rule_engine_webthing.py
openhab_pythonrule_engine/source_scanner.py
openhab_pythonrule_engine-1.2.28.dist-info/LICENSE
openhab_pythonrule_engine-1.2.28.dist-info/METADATA
openhab_pythonrule_engine-1.2.28.dist-info/WHEEL
openhab_pythonrule_engine-1.2.28.dist-info/entry_points.txt
openhab_pythonrule_engine-1.2.28.dist-info/top_level.txt
openhab_pythonrule_engine-1.2.28.dist-info/RECORD
